{
  "timestamp": "2026-03-23T22:44:51.259613",
  "parameters": {
    "games_per_matchup": 4,
    "profondeur": 4,
    "simu_montecarlo": 15
  },
  "results": {
    "montecarlo_vs_random": {
      "s1_wins": 4,
      "s2_wins": 0,
      "draws": 0,
      "games": [
        {
          "game_num": 1,
          "s1": "montecarlo",
          "s2": "random",
          "winner": "montecarlo",
          "result": "X",
          "moves": 62,
          "timestamp": "2026-03-23T22:37:12.372540"
        },
        {
          "game_num": 2,
          "s1": "montecarlo",
          "s2": "random",
          "winner": "montecarlo",
          "result": "X",
          "moves": 63,
          "timestamp": "2026-03-23T22:37:16.256303"
        },
        {
          "game_num": 3,
          "s1": "montecarlo",
          "s2": "random",
          "winner": "montecarlo",
          "result": "X",
          "moves": 63,
          "timestamp": "2026-03-23T22:37:20.708894"
        },
        {
          "game_num": 4,
          "s1": "montecarlo",
          "s2": "random",
          "winner": "montecarlo",
          "result": "X",
          "moves": 62,
          "timestamp": "2026-03-23T22:37:24.949424"
        }
      ]
    },
    "montecarlo_vs_poids": {
      "s1_wins": 3,
      "s2_wins": 1,
      "draws": 0,
      "games": [
        {
          "game_num": 1,
          "s1": "montecarlo",
          "s2": "poids",
          "winner": "poids",
          "result": "O",
          "moves": 62,
          "timestamp": "2026-03-23T22:37:32.420186"
        },
        {
          "game_num": 2,
          "s1": "montecarlo",
          "s2": "poids",
          "winner": "montecarlo",
          "result": "X",
          "moves": 63,
          "timestamp": "2026-03-23T22:37:38.943147"
        },
        {
          "game_num": 3,
          "s1": "montecarlo",
          "s2": "poids",
          "winner": "montecarlo",
          "result": "X",
          "moves": 62,
          "timestamp": "2026-03-23T22:37:46.265572"
        },
        {
          "game_num": 4,
          "s1": "montecarlo",
          "s2": "poids",
          "winner": "montecarlo",
          "result": "X",
          "moves": 63,
          "timestamp": "2026-03-23T22:37:53.606705"
        }
      ]
    },
    "montecarlo_vs_mobilite": {
      "s1_wins": 2,
      "s2_wins": 2,
      "draws": 0,
      "games": [
        {
          "game_num": 1,
          "s1": "montecarlo",
          "s2": "mobilite",
          "winner": "montecarlo",
          "result": "X",
          "moves": 65,
          "timestamp": "2026-03-23T22:37:59.770844"
        },
        {
          "game_num": 2,
          "s1": "montecarlo",
          "s2": "mobilite",
          "winner": "mobilite",
          "result": "O",
          "moves": 64,
          "timestamp": "2026-03-23T22:38:05.953819"
        },
        {
          "game_num": 3,
          "s1": "montecarlo",
          "s2": "mobilite",
          "winner": "mobilite",
          "result": "O",
          "moves": 62,
          "timestamp": "2026-03-23T22:38:11.821166"
        },
        {
          "game_num": 4,
          "s1": "montecarlo",
          "s2": "mobilite",
          "winner": "montecarlo",
          "result": "X",
          "moves": 63,
          "timestamp": "2026-03-23T22:38:18.557015"
        }
      ]
    },
    "montecarlo_vs_mixte": {
      "s1_wins": 4,
      "s2_wins": 0,
      "draws": 0,
      "games": [
        {
          "game_num": 1,
          "s1": "montecarlo",
          "s2": "mixte",
          "winner": "montecarlo",
          "result": "X",
          "moves": 62,
          "timestamp": "2026-03-23T22:38:24.105163"
        },
        {
          "game_num": 2,
          "s1": "montecarlo",
          "s2": "mixte",
          "winner": "montecarlo",
          "result": "X",
          "moves": 69,
          "timestamp": "2026-03-23T22:38:30.900012"
        },
        {
          "game_num": 3,
          "s1": "montecarlo",
          "s2": "mixte",
          "winner": "montecarlo",
          "result": "X",
          "moves": 63,
          "timestamp": "2026-03-23T22:38:39.084516"
        },
        {
          "game_num": 4,
          "s1": "montecarlo",
          "s2": "mixte",
          "winner": "montecarlo",
          "result": "X",
          "moves": 62,
          "timestamp": "2026-03-23T22:38:46.053223"
        }
      ]
    },
    "montecarlo_vs_absolu": {
      "s1_wins": 4,
      "s2_wins": 0,
      "draws": 0,
      "games": [
        {
          "game_num": 1,
          "s1": "montecarlo",
          "s2": "absolu",
          "winner": "montecarlo",
          "result": "X",
          "moves": 63,
          "timestamp": "2026-03-23T22:38:53.840369"
        },
        {
          "game_num": 2,
          "s1": "montecarlo",
          "s2": "absolu",
          "winner": "montecarlo",
          "result": "X",
          "moves": 63,
          "timestamp": "2026-03-23T22:39:01.218353"
        },
        {
          "game_num": 3,
          "s1": "montecarlo",
          "s2": "absolu",
          "winner": "montecarlo",
          "result": "X",
          "moves": 63,
          "timestamp": "2026-03-23T22:39:07.208877"
        },
        {
          "game_num": 4,
          "s1": "montecarlo",
          "s2": "absolu",
          "winner": "montecarlo",
          "result": "X",
          "moves": 64,
          "timestamp": "2026-03-23T22:39:12.148773"
        }
      ]
    },
    "random_vs_montecarlo": {
      "s1_wins": 0,
      "s2_wins": 4,
      "draws": 0,
      "games": [
        {
          "game_num": 1,
          "s1": "random",
          "s2": "montecarlo",
          "winner": "montecarlo",
          "result": "O",
          "moves": 62,
          "timestamp": "2026-03-23T22:39:16.474120"
        },
        {
          "game_num": 2,
          "s1": "random",
          "s2": "montecarlo",
          "winner": "montecarlo",
          "result": "O",
          "moves": 62,
          "timestamp": "2026-03-23T22:39:21.515921"
        },
        {
          "game_num": 3,
          "s1": "random",
          "s2": "montecarlo",
          "winner": "montecarlo",
          "result": "O",
          "moves": 62,
          "timestamp": "2026-03-23T22:39:25.049657"
        },
        {
          "game_num": 4,
          "s1": "random",
          "s2": "montecarlo",
          "winner": "montecarlo",
          "result": "O",
          "moves": 62,
          "timestamp": "2026-03-23T22:39:29.456000"
        }
      ]
    },
    "random_vs_poids": {
      "s1_wins": 3,
      "s2_wins": 1,
      "draws": 0,
      "games": [
        {
          "game_num": 1,
          "s1": "random",
          "s2": "poids",
          "winner": "random",
          "result": "X",
          "moves": 63,
          "timestamp": "2026-03-23T22:39:32.543418"
        },
        {
          "game_num": 2,
          "s1": "random",
          "s2": "poids",
          "winner": "poids",
          "result": "O",
          "moves": 62,
          "timestamp": "2026-03-23T22:39:33.876036"
        },
        {
          "game_num": 3,
          "s1": "random",
          "s2": "poids",
          "winner": "random",
          "result": "X",
          "moves": 63,
          "timestamp": "2026-03-23T22:39:39.635738"
        },
        {
          "game_num": 4,
          "s1": "random",
          "s2": "poids",
          "winner": "random",
          "result": "X",
          "moves": 63,
          "timestamp": "2026-03-23T22:39:42.535205"
        }
      ]
    },
    "random_vs_mobilite": {
      "s1_wins": 2,
      "s2_wins": 2,
      "draws": 0,
      "games": [
        {
          "game_num": 1,
          "s1": "random",
          "s2": "mobilite",
          "winner": "mobilite",
          "result": "O",
          "moves": 62,
          "timestamp": "2026-03-23T22:39:45.705183"
        },
        {
          "game_num": 2,
          "s1": "random",
          "s2": "mobilite",
          "winner": "random",
          "result": "X",
          "moves": 63,
          "timestamp": "2026-03-23T22:39:48.477773"
        },
        {
          "game_num": 3,
          "s1": "random",
          "s2": "mobilite",
          "winner": "random",
          "result": "X",
          "moves": 63,
          "timestamp": "2026-03-23T22:39:50.638399"
        },
        {
          "game_num": 4,
          "s1": "random",
          "s2": "mobilite",
          "winner": "mobilite",
          "result": "O",
          "moves": 63,
          "timestamp": "2026-03-23T22:39:52.521596"
        }
      ]
    },
    "random_vs_mixte": {
      "s1_wins": 1,
      "s2_wins": 3,
      "draws": 0,
      "games": [
        {
          "game_num": 1,
          "s1": "random",
          "s2": "mixte",
          "winner": "mixte",
          "result": "O",
          "moves": 62,
          "timestamp": "2026-03-23T22:39:54.112935"
        },
        {
          "game_num": 2,
          "s1": "random",
          "s2": "mixte",
          "winner": "random",
          "result": "X",
          "moves": 63,
          "timestamp": "2026-03-23T22:39:55.506516"
        },
        {
          "game_num": 3,
          "s1": "random",
          "s2": "mixte",
          "winner": "mixte",
          "result": "O",
          "moves": 62,
          "timestamp": "2026-03-23T22:39:57.953790"
        },
        {
          "game_num": 4,
          "s1": "random",
          "s2": "mixte",
          "winner": "mixte",
          "result": "O",
          "moves": 62,
          "timestamp": "2026-03-23T22:39:59.312402"
        }
      ]
    },
    "random_vs_absolu": {
      "s1_wins": 0,
      "s2_wins": 4,
      "draws": 0,
      "games": [
        {
          "game_num": 1,
          "s1": "random",
          "s2": "absolu",
          "winner": "absolu",
          "result": "O",
          "moves": 62,
          "timestamp": "2026-03-23T22:40:03.678592"
        },
        {
          "game_num": 2,
          "s1": "random",
          "s2": "absolu",
          "winner": "absolu",
          "result": "O",
          "moves": 62,
          "timestamp": "2026-03-23T22:40:05.676587"
        },
        {
          "game_num": 3,
          "s1": "random",
          "s2": "absolu",
          "winner": "absolu",
          "result": "O",
          "moves": 63,
          "timestamp": "2026-03-23T22:40:08.036556"
        },
        {
          "game_num": 4,
          "s1": "random",
          "s2": "absolu",
          "winner": "absolu",
          "result": "O",
          "moves": 63,
          "timestamp": "2026-03-23T22:40:10.837309"
        }
      ]
    },
    "poids_vs_montecarlo": {
      "s1_wins": 0,
      "s2_wins": 4,
      "draws": 0,
      "games": [
        {
          "game_num": 1,
          "s1": "poids",
          "s2": "montecarlo",
          "winner": "montecarlo",
          "result": "O",
          "moves": 66,
          "timestamp": "2026-03-23T22:40:15.216204"
        },
        {
          "game_num": 2,
          "s1": "poids",
          "s2": "montecarlo",
          "winner": "montecarlo",
          "result": "O",
          "moves": 68,
          "timestamp": "2026-03-23T22:40:18.971505"
        },
        {
          "game_num": 3,
          "s1": "poids",
          "s2": "montecarlo",
          "winner": "montecarlo",
          "result": "O",
          "moves": 63,
          "timestamp": "2026-03-23T22:40:24.568977"
        },
        {
          "game_num": 4,
          "s1": "poids",
          "s2": "montecarlo",
          "winner": "montecarlo",
          "result": "O",
          "moves": 64,
          "timestamp": "2026-03-23T22:40:28.722086"
        }
      ]
    },
    "poids_vs_random": {
      "s1_wins": 2,
      "s2_wins": 2,
      "draws": 0,
      "games": [
        {
          "game_num": 1,
          "s1": "poids",
          "s2": "random",
          "winner": "poids",
          "result": "X",
          "moves": 62,
          "timestamp": "2026-03-23T22:40:30.372196"
        },
        {
          "game_num": 2,
          "s1": "poids",
          "s2": "random",
          "winner": "random",
          "result": "O",
          "moves": 62,
          "timestamp": "2026-03-23T22:40:32.818981"
        },
        {
          "game_num": 3,
          "s1": "poids",
          "s2": "random",
          "winner": "random",
          "result": "O",
          "moves": 62,
          "timestamp": "2026-03-23T22:40:33.923011"
        },
        {
          "game_num": 4,
          "s1": "poids",
          "s2": "random",
          "winner": "poids",
          "result": "X",
          "moves": 62,
          "timestamp": "2026-03-23T22:40:34.830519"
        }
      ]
    },
    "poids_vs_mobilite": {
      "s1_wins": 4,
      "s2_wins": 0,
      "draws": 0,
      "games": [
        {
          "game_num": 1,
          "s1": "poids",
          "s2": "mobilite",
          "winner": "poids",
          "result": "X",
          "moves": 62,
          "timestamp": "2026-03-23T22:40:37.893950"
        },
        {
          "game_num": 2,
          "s1": "poids",
          "s2": "mobilite",
          "winner": "poids",
          "result": "X",
          "moves": 62,
          "timestamp": "2026-03-23T22:40:40.981935"
        },
        {
          "game_num": 3,
          "s1": "poids",
          "s2": "mobilite",
          "winner": "poids",
          "result": "X",
          "moves": 62,
          "timestamp": "2026-03-23T22:40:44.053223"
        },
        {
          "game_num": 4,
          "s1": "poids",
          "s2": "mobilite",
          "winner": "poids",
          "result": "X",
          "moves": 62,
          "timestamp": "2026-03-23T22:40:47.243788"
        }
      ]
    },
    "poids_vs_mixte": {
      "s1_wins": 4,
      "s2_wins": 0,
      "draws": 0,
      "games": [
        {
          "game_num": 1,
          "s1": "poids",
          "s2": "mixte",
          "winner": "poids",
          "result": "X",
          "moves": 62,
          "timestamp": "2026-03-23T22:40:50.361394"
        },
        {
          "game_num": 2,
          "s1": "poids",
          "s2": "mixte",
          "winner": "poids",
          "result": "X",
          "moves": 62,
          "timestamp": "2026-03-23T22:40:53.472970"
        },
        {
          "game_num": 3,
          "s1": "poids",
          "s2": "mixte",
          "winner": "poids",
          "result": "X",
          "moves": 62,
          "timestamp": "2026-03-23T22:40:56.571778"
        },
        {
          "game_num": 4,
          "s1": "poids",
          "s2": "mixte",
          "winner": "poids",
          "result": "X",
          "moves": 62,
          "timestamp": "2026-03-23T22:40:59.681172"
        }
      ]
    },
    "poids_vs_absolu": {
      "s1_wins": 4,
      "s2_wins": 0,
      "draws": 0,
      "games": [
        {
          "game_num": 1,
          "s1": "poids",
          "s2": "absolu",
          "winner": "poids",
          "result": "X",
          "moves": 62,
          "timestamp": "2026-03-23T22:41:02.887061"
        },
        {
          "game_num": 2,
          "s1": "poids",
          "s2": "absolu",
          "winner": "poids",
          "result": "X",
          "moves": 62,
          "timestamp": "2026-03-23T22:41:05.969738"
        },
        {
          "game_num": 3,
          "s1": "poids",
          "s2": "absolu",
          "winner": "poids",
          "result": "X",
          "moves": 62,
          "timestamp": "2026-03-23T22:41:09.095382"
        },
        {
          "game_num": 4,
          "s1": "poids",
          "s2": "absolu",
          "winner": "poids",
          "result": "X",
          "moves": 62,
          "timestamp": "2026-03-23T22:41:12.155914"
        }
      ]
    },
    "mobilite_vs_montecarlo": {
      "s1_wins": 1,
      "s2_wins": 3,
      "draws": 0,
      "games": [
        {
          "game_num": 1,
          "s1": "mobilite",
          "s2": "montecarlo",
          "winner": "montecarlo",
          "result": "O",
          "moves": 62,
          "timestamp": "2026-03-23T22:41:17.575717"
        },
        {
          "game_num": 2,
          "s1": "mobilite",
          "s2": "montecarlo",
          "winner": "montecarlo",
          "result": "O",
          "moves": 63,
          "timestamp": "2026-03-23T22:41:22.536549"
        },
        {
          "game_num": 3,
          "s1": "mobilite",
          "s2": "montecarlo",
          "winner": "montecarlo",
          "result": "O",
          "moves": 62,
          "timestamp": "2026-03-23T22:41:28.851234"
        },
        {
          "game_num": 4,
          "s1": "mobilite",
          "s2": "montecarlo",
          "winner": "mobilite",
          "result": "X",
          "moves": 63,
          "timestamp": "2026-03-23T22:41:33.909865"
        }
      ]
    },
    "mobilite_vs_random": {
      "s1_wins": 4,
      "s2_wins": 0,
      "draws": 0,
      "games": [
        {
          "game_num": 1,
          "s1": "mobilite",
          "s2": "random",
          "winner": "mobilite",
          "result": "X",
          "moves": 63,
          "timestamp": "2026-03-23T22:41:37.747070"
        },
        {
          "game_num": 2,
          "s1": "mobilite",
          "s2": "random",
          "winner": "mobilite",
          "result": "X",
          "moves": 63,
          "timestamp": "2026-03-23T22:41:39.488878"
        },
        {
          "game_num": 3,
          "s1": "mobilite",
          "s2": "random",
          "winner": "mobilite",
          "result": "X",
          "moves": 62,
          "timestamp": "2026-03-23T22:41:43.591032"
        },
        {
          "game_num": 4,
          "s1": "mobilite",
          "s2": "random",
          "winner": "mobilite",
          "result": "X",
          "moves": 62,
          "timestamp": "2026-03-23T22:41:45.248133"
        }
      ]
    },
    "mobilite_vs_poids": {
      "s1_wins": 4,
      "s2_wins": 0,
      "draws": 0,
      "games": [
        {
          "game_num": 1,
          "s1": "mobilite",
          "s2": "poids",
          "winner": "mobilite",
          "result": "X",
          "moves": 62,
          "timestamp": "2026-03-23T22:41:48.322651"
        },
        {
          "game_num": 2,
          "s1": "mobilite",
          "s2": "poids",
          "winner": "mobilite",
          "result": "X",
          "moves": 62,
          "timestamp": "2026-03-23T22:41:51.529249"
        },
        {
          "game_num": 3,
          "s1": "mobilite",
          "s2": "poids",
          "winner": "mobilite",
          "result": "X",
          "moves": 62,
          "timestamp": "2026-03-23T22:41:54.775060"
        },
        {
          "game_num": 4,
          "s1": "mobilite",
          "s2": "poids",
          "winner": "mobilite",
          "result": "X",
          "moves": 62,
          "timestamp": "2026-03-23T22:41:57.828520"
        }
      ]
    },
    "mobilite_vs_mixte": {
      "s1_wins": 4,
      "s2_wins": 0,
      "draws": 0,
      "games": [
        {
          "game_num": 1,
          "s1": "mobilite",
          "s2": "mixte",
          "winner": "mobilite",
          "result": "X",
          "moves": 62,
          "timestamp": "2026-03-23T22:42:01.007949"
        },
        {
          "game_num": 2,
          "s1": "mobilite",
          "s2": "mixte",
          "winner": "mobilite",
          "result": "X",
          "moves": 62,
          "timestamp": "2026-03-23T22:42:04.094822"
        },
        {
          "game_num": 3,
          "s1": "mobilite",
          "s2": "mixte",
          "winner": "mobilite",
          "result": "X",
          "moves": 62,
          "timestamp": "2026-03-23T22:42:07.137530"
        },
        {
          "game_num": 4,
          "s1": "mobilite",
          "s2": "mixte",
          "winner": "mobilite",
          "result": "X",
          "moves": 62,
          "timestamp": "2026-03-23T22:42:10.182600"
        }
      ]
    },
    "mobilite_vs_absolu": {
      "s1_wins": 4,
      "s2_wins": 0,
      "draws": 0,
      "games": [
        {
          "game_num": 1,
          "s1": "mobilite",
          "s2": "absolu",
          "winner": "mobilite",
          "result": "X",
          "moves": 62,
          "timestamp": "2026-03-23T22:42:13.238947"
        },
        {
          "game_num": 2,
          "s1": "mobilite",
          "s2": "absolu",
          "winner": "mobilite",
          "result": "X",
          "moves": 62,
          "timestamp": "2026-03-23T22:42:16.298827"
        },
        {
          "game_num": 3,
          "s1": "mobilite",
          "s2": "absolu",
          "winner": "mobilite",
          "result": "X",
          "moves": 62,
          "timestamp": "2026-03-23T22:42:19.347602"
        },
        {
          "game_num": 4,
          "s1": "mobilite",
          "s2": "absolu",
          "winner": "mobilite",
          "result": "X",
          "moves": 62,
          "timestamp": "2026-03-23T22:42:22.735400"
        }
      ]
    },
    "mixte_vs_montecarlo": {
      "s1_wins": 0,
      "s2_wins": 4,
      "draws": 0,
      "games": [
        {
          "game_num": 1,
          "s1": "mixte",
          "s2": "montecarlo",
          "winner": "montecarlo",
          "result": "O",
          "moves": 65,
          "timestamp": "2026-03-23T22:42:27.543602"
        },
        {
          "game_num": 2,
          "s1": "mixte",
          "s2": "montecarlo",
          "winner": "montecarlo",
          "result": "O",
          "moves": 63,
          "timestamp": "2026-03-23T22:42:32.432737"
        },
        {
          "game_num": 3,
          "s1": "mixte",
          "s2": "montecarlo",
          "winner": "montecarlo",
          "result": "O",
          "moves": 62,
          "timestamp": "2026-03-23T22:42:37.924329"
        },
        {
          "game_num": 4,
          "s1": "mixte",
          "s2": "montecarlo",
          "winner": "montecarlo",
          "result": "O",
          "moves": 62,
          "timestamp": "2026-03-23T22:42:44.528259"
        }
      ]
    },
    "mixte_vs_random": {
      "s1_wins": 1,
      "s2_wins": 2,
      "draws": 1,
      "games": [
        {
          "game_num": 1,
          "s1": "mixte",
          "s2": "random",
          "winner": "random",
          "result": "O",
          "moves": 64,
          "timestamp": "2026-03-23T22:42:46.048832"
        },
        {
          "game_num": 2,
          "s1": "mixte",
          "s2": "random",
          "winner": "random",
          "result": "O",
          "moves": 62,
          "timestamp": "2026-03-23T22:42:48.167565"
        },
        {
          "game_num": 3,
          "s1": "mixte",
          "s2": "random",
          "winner": "Égalité",
          "result": "Egalite",
          "moves": 62,
          "timestamp": "2026-03-23T22:42:49.623443"
        },
        {
          "game_num": 4,
          "s1": "mixte",
          "s2": "random",
          "winner": "mixte",
          "result": "X",
          "moves": 62,
          "timestamp": "2026-03-23T22:42:52.216771"
        }
      ]
    },
    "mixte_vs_poids": {
      "s1_wins": 4,
      "s2_wins": 0,
      "draws": 0,
      "games": [
        {
          "game_num": 1,
          "s1": "mixte",
          "s2": "poids",
          "winner": "mixte",
          "result": "X",
          "moves": 62,
          "timestamp": "2026-03-23T22:42:55.767470"
        },
        {
          "game_num": 2,
          "s1": "mixte",
          "s2": "poids",
          "winner": "mixte",
          "result": "X",
          "moves": 62,
          "timestamp": "2026-03-23T22:42:59.046892"
        },
        {
          "game_num": 3,
          "s1": "mixte",
          "s2": "poids",
          "winner": "mixte",
          "result": "X",
          "moves": 62,
          "timestamp": "2026-03-23T22:43:02.573148"
        },
        {
          "game_num": 4,
          "s1": "mixte",
          "s2": "poids",
          "winner": "mixte",
          "result": "X",
          "moves": 62,
          "timestamp": "2026-03-23T22:43:06.187206"
        }
      ]
    },
    "mixte_vs_mobilite": {
      "s1_wins": 4,
      "s2_wins": 0,
      "draws": 0,
      "games": [
        {
          "game_num": 1,
          "s1": "mixte",
          "s2": "mobilite",
          "winner": "mixte",
          "result": "X",
          "moves": 62,
          "timestamp": "2026-03-23T22:43:09.492398"
        },
        {
          "game_num": 2,
          "s1": "mixte",
          "s2": "mobilite",
          "winner": "mixte",
          "result": "X",
          "moves": 62,
          "timestamp": "2026-03-23T22:43:13.319342"
        },
        {
          "game_num": 3,
          "s1": "mixte",
          "s2": "mobilite",
          "winner": "mixte",
          "result": "X",
          "moves": 62,
          "timestamp": "2026-03-23T22:43:17.648630"
        },
        {
          "game_num": 4,
          "s1": "mixte",
          "s2": "mobilite",
          "winner": "mixte",
          "result": "X",
          "moves": 62,
          "timestamp": "2026-03-23T22:43:21.285774"
        }
      ]
    },
    "mixte_vs_absolu": {
      "s1_wins": 4,
      "s2_wins": 0,
      "draws": 0,
      "games": [
        {
          "game_num": 1,
          "s1": "mixte",
          "s2": "absolu",
          "winner": "mixte",
          "result": "X",
          "moves": 62,
          "timestamp": "2026-03-23T22:43:25.024215"
        },
        {
          "game_num": 2,
          "s1": "mixte",
          "s2": "absolu",
          "winner": "mixte",
          "result": "X",
          "moves": 62,
          "timestamp": "2026-03-23T22:43:28.709204"
        },
        {
          "game_num": 3,
          "s1": "mixte",
          "s2": "absolu",
          "winner": "mixte",
          "result": "X",
          "moves": 62,
          "timestamp": "2026-03-23T22:43:32.095439"
        },
        {
          "game_num": 4,
          "s1": "mixte",
          "s2": "absolu",
          "winner": "mixte",
          "result": "X",
          "moves": 62,
          "timestamp": "2026-03-23T22:43:35.611577"
        }
      ]
    },
    "absolu_vs_montecarlo": {
      "s1_wins": 1,
      "s2_wins": 3,
      "draws": 0,
      "games": [
        {
          "game_num": 1,
          "s1": "absolu",
          "s2": "montecarlo",
          "winner": "montecarlo",
          "result": "O",
          "moves": 62,
          "timestamp": "2026-03-23T22:43:40.839255"
        },
        {
          "game_num": 2,
          "s1": "absolu",
          "s2": "montecarlo",
          "winner": "montecarlo",
          "result": "O",
          "moves": 63,
          "timestamp": "2026-03-23T22:43:48.093553"
        },
        {
          "game_num": 3,
          "s1": "absolu",
          "s2": "montecarlo",
          "winner": "montecarlo",
          "result": "O",
          "moves": 64,
          "timestamp": "2026-03-23T22:43:53.188891"
        },
        {
          "game_num": 4,
          "s1": "absolu",
          "s2": "montecarlo",
          "winner": "absolu",
          "result": "X",
          "moves": 63,
          "timestamp": "2026-03-23T22:43:59.216474"
        }
      ]
    },
    "absolu_vs_random": {
      "s1_wins": 1,
      "s2_wins": 3,
      "draws": 0,
      "games": [
        {
          "game_num": 1,
          "s1": "absolu",
          "s2": "random",
          "winner": "random",
          "result": "O",
          "moves": 62,
          "timestamp": "2026-03-23T22:44:00.453019"
        },
        {
          "game_num": 2,
          "s1": "absolu",
          "s2": "random",
          "winner": "random",
          "result": "O",
          "moves": 66,
          "timestamp": "2026-03-23T22:44:02.960254"
        },
        {
          "game_num": 3,
          "s1": "absolu",
          "s2": "random",
          "winner": "absolu",
          "result": "X",
          "moves": 63,
          "timestamp": "2026-03-23T22:44:06.127240"
        },
        {
          "game_num": 4,
          "s1": "absolu",
          "s2": "random",
          "winner": "random",
          "result": "O",
          "moves": 64,
          "timestamp": "2026-03-23T22:44:08.770309"
        }
      ]
    },
    "absolu_vs_poids": {
      "s1_wins": 4,
      "s2_wins": 0,
      "draws": 0,
      "games": [
        {
          "game_num": 1,
          "s1": "absolu",
          "s2": "poids",
          "winner": "absolu",
          "result": "X",
          "moves": 62,
          "timestamp": "2026-03-23T22:44:12.224037"
        },
        {
          "game_num": 2,
          "s1": "absolu",
          "s2": "poids",
          "winner": "absolu",
          "result": "X",
          "moves": 62,
          "timestamp": "2026-03-23T22:44:15.592660"
        },
        {
          "game_num": 3,
          "s1": "absolu",
          "s2": "poids",
          "winner": "absolu",
          "result": "X",
          "moves": 62,
          "timestamp": "2026-03-23T22:44:19.167760"
        },
        {
          "game_num": 4,
          "s1": "absolu",
          "s2": "poids",
          "winner": "absolu",
          "result": "X",
          "moves": 62,
          "timestamp": "2026-03-23T22:44:22.702131"
        }
      ]
    },
    "absolu_vs_mobilite": {
      "s1_wins": 4,
      "s2_wins": 0,
      "draws": 0,
      "games": [
        {
          "game_num": 1,
          "s1": "absolu",
          "s2": "mobilite",
          "winner": "absolu",
          "result": "X",
          "moves": 62,
          "timestamp": "2026-03-23T22:44:26.291242"
        },
        {
          "game_num": 2,
          "s1": "absolu",
          "s2": "mobilite",
          "winner": "absolu",
          "result": "X",
          "moves": 62,
          "timestamp": "2026-03-23T22:44:29.864532"
        },
        {
          "game_num": 3,
          "s1": "absolu",
          "s2": "mobilite",
          "winner": "absolu",
          "result": "X",
          "moves": 62,
          "timestamp": "2026-03-23T22:44:33.452830"
        },
        {
          "game_num": 4,
          "s1": "absolu",
          "s2": "mobilite",
          "winner": "absolu",
          "result": "X",
          "moves": 62,
          "timestamp": "2026-03-23T22:44:37.032967"
        }
      ]
    },
    "absolu_vs_mixte": {
      "s1_wins": 4,
      "s2_wins": 0,
      "draws": 0,
      "games": [
        {
          "game_num": 1,
          "s1": "absolu",
          "s2": "mixte",
          "winner": "absolu",
          "result": "X",
          "moves": 62,
          "timestamp": "2026-03-23T22:44:40.562133"
        },
        {
          "game_num": 2,
          "s1": "absolu",
          "s2": "mixte",
          "winner": "absolu",
          "result": "X",
          "moves": 62,
          "timestamp": "2026-03-23T22:44:44.248482"
        },
        {
          "game_num": 3,
          "s1": "absolu",
          "s2": "mixte",
          "winner": "absolu",
          "result": "X",
          "moves": 62,
          "timestamp": "2026-03-23T22:44:47.721037"
        },
        {
          "game_num": 4,
          "s1": "absolu",
          "s2": "mixte",
          "winner": "absolu",
          "result": "X",
          "moves": 62,
          "timestamp": "2026-03-23T22:44:51.256702"
        }
      ]
    }
  },
  "logs": [
    {
      "game_num": 1,
      "s1": "montecarlo",
      "s2": "random",
      "winner": "montecarlo",
      "result": "X",
      "moves": 62,
      "timestamp": "2026-03-23T22:37:12.372540"
    },
    {
      "game_num": 2,
      "s1": "montecarlo",
      "s2": "random",
      "winner": "montecarlo",
      "result": "X",
      "moves": 63,
      "timestamp": "2026-03-23T22:37:16.256303"
    },
    {
      "game_num": 3,
      "s1": "montecarlo",
      "s2": "random",
      "winner": "montecarlo",
      "result": "X",
      "moves": 63,
      "timestamp": "2026-03-23T22:37:20.708894"
    },
    {
      "game_num": 4,
      "s1": "montecarlo",
      "s2": "random",
      "winner": "montecarlo",
      "result": "X",
      "moves": 62,
      "timestamp": "2026-03-23T22:37:24.949424"
    },
    {
      "game_num": 1,
      "s1": "montecarlo",
      "s2": "poids",
      "winner": "poids",
      "result": "O",
      "moves": 62,
      "timestamp": "2026-03-23T22:37:32.420186"
    },
    {
      "game_num": 2,
      "s1": "montecarlo",
      "s2": "poids",
      "winner": "montecarlo",
      "result": "X",
      "moves": 63,
      "timestamp": "2026-03-23T22:37:38.943147"
    },
    {
      "game_num": 3,
      "s1": "montecarlo",
      "s2": "poids",
      "winner": "montecarlo",
      "result": "X",
      "moves": 62,
      "timestamp": "2026-03-23T22:37:46.265572"
    },
    {
      "game_num": 4,
      "s1": "montecarlo",
      "s2": "poids",
      "winner": "montecarlo",
      "result": "X",
      "moves": 63,
      "timestamp": "2026-03-23T22:37:53.606705"
    },
    {
      "game_num": 1,
      "s1": "montecarlo",
      "s2": "mobilite",
      "winner": "montecarlo",
      "result": "X",
      "moves": 65,
      "timestamp": "2026-03-23T22:37:59.770844"
    },
    {
      "game_num": 2,
      "s1": "montecarlo",
      "s2": "mobilite",
      "winner": "mobilite",
      "result": "O",
      "moves": 64,
      "timestamp": "2026-03-23T22:38:05.953819"
    },
    {
      "game_num": 3,
      "s1": "montecarlo",
      "s2": "mobilite",
      "winner": "mobilite",
      "result": "O",
      "moves": 62,
      "timestamp": "2026-03-23T22:38:11.821166"
    },
    {
      "game_num": 4,
      "s1": "montecarlo",
      "s2": "mobilite",
      "winner": "montecarlo",
      "result": "X",
      "moves": 63,
      "timestamp": "2026-03-23T22:38:18.557015"
    },
    {
      "game_num": 1,
      "s1": "montecarlo",
      "s2": "mixte",
      "winner": "montecarlo",
      "result": "X",
      "moves": 62,
      "timestamp": "2026-03-23T22:38:24.105163"
    },
    {
      "game_num": 2,
      "s1": "montecarlo",
      "s2": "mixte",
      "winner": "montecarlo",
      "result": "X",
      "moves": 69,
      "timestamp": "2026-03-23T22:38:30.900012"
    },
    {
      "game_num": 3,
      "s1": "montecarlo",
      "s2": "mixte",
      "winner": "montecarlo",
      "result": "X",
      "moves": 63,
      "timestamp": "2026-03-23T22:38:39.084516"
    },
    {
      "game_num": 4,
      "s1": "montecarlo",
      "s2": "mixte",
      "winner": "montecarlo",
      "result": "X",
      "moves": 62,
      "timestamp": "2026-03-23T22:38:46.053223"
    },
    {
      "game_num": 1,
      "s1": "montecarlo",
      "s2": "absolu",
      "winner": "montecarlo",
      "result": "X",
      "moves": 63,
      "timestamp": "2026-03-23T22:38:53.840369"
    },
    {
      "game_num": 2,
      "s1": "montecarlo",
      "s2": "absolu",
      "winner": "montecarlo",
      "result": "X",
      "moves": 63,
      "timestamp": "2026-03-23T22:39:01.218353"
    },
    {
      "game_num": 3,
      "s1": "montecarlo",
      "s2": "absolu",
      "winner": "montecarlo",
      "result": "X",
      "moves": 63,
      "timestamp": "2026-03-23T22:39:07.208877"
    },
    {
      "game_num": 4,
      "s1": "montecarlo",
      "s2": "absolu",
      "winner": "montecarlo",
      "result": "X",
      "moves": 64,
      "timestamp": "2026-03-23T22:39:12.148773"
    },
    {
      "game_num": 1,
      "s1": "random",
      "s2": "montecarlo",
      "winner": "montecarlo",
      "result": "O",
      "moves": 62,
      "timestamp": "2026-03-23T22:39:16.474120"
    },
    {
      "game_num": 2,
      "s1": "random",
      "s2": "montecarlo",
      "winner": "montecarlo",
      "result": "O",
      "moves": 62,
      "timestamp": "2026-03-23T22:39:21.515921"
    },
    {
      "game_num": 3,
      "s1": "random",
      "s2": "montecarlo",
      "winner": "montecarlo",
      "result": "O",
      "moves": 62,
      "timestamp": "2026-03-23T22:39:25.049657"
    },
    {
      "game_num": 4,
      "s1": "random",
      "s2": "montecarlo",
      "winner": "montecarlo",
      "result": "O",
      "moves": 62,
      "timestamp": "2026-03-23T22:39:29.456000"
    },
    {
      "game_num": 1,
      "s1": "random",
      "s2": "poids",
      "winner": "random",
      "result": "X",
      "moves": 63,
      "timestamp": "2026-03-23T22:39:32.543418"
    },
    {
      "game_num": 2,
      "s1": "random",
      "s2": "poids",
      "winner": "poids",
      "result": "O",
      "moves": 62,
      "timestamp": "2026-03-23T22:39:33.876036"
    },
    {
      "game_num": 3,
      "s1": "random",
      "s2": "poids",
      "winner": "random",
      "result": "X",
      "moves": 63,
      "timestamp": "2026-03-23T22:39:39.635738"
    },
    {
      "game_num": 4,
      "s1": "random",
      "s2": "poids",
      "winner": "random",
      "result": "X",
      "moves": 63,
      "timestamp": "2026-03-23T22:39:42.535205"
    },
    {
      "game_num": 1,
      "s1": "random",
      "s2": "mobilite",
      "winner": "mobilite",
      "result": "O",
      "moves": 62,
      "timestamp": "2026-03-23T22:39:45.705183"
    },
    {
      "game_num": 2,
      "s1": "random",
      "s2": "mobilite",
      "winner": "random",
      "result": "X",
      "moves": 63,
      "timestamp": "2026-03-23T22:39:48.477773"
    },
    {
      "game_num": 3,
      "s1": "random",
      "s2": "mobilite",
      "winner": "random",
      "result": "X",
      "moves": 63,
      "timestamp": "2026-03-23T22:39:50.638399"
    },
    {
      "game_num": 4,
      "s1": "random",
      "s2": "mobilite",
      "winner": "mobilite",
      "result": "O",
      "moves": 63,
      "timestamp": "2026-03-23T22:39:52.521596"
    },
    {
      "game_num": 1,
      "s1": "random",
      "s2": "mixte",
      "winner": "mixte",
      "result": "O",
      "moves": 62,
      "timestamp": "2026-03-23T22:39:54.112935"
    },
    {
      "game_num": 2,
      "s1": "random",
      "s2": "mixte",
      "winner": "random",
      "result": "X",
      "moves": 63,
      "timestamp": "2026-03-23T22:39:55.506516"
    },
    {
      "game_num": 3,
      "s1": "random",
      "s2": "mixte",
      "winner": "mixte",
      "result": "O",
      "moves": 62,
      "timestamp": "2026-03-23T22:39:57.953790"
    },
    {
      "game_num": 4,
      "s1": "random",
      "s2": "mixte",
      "winner": "mixte",
      "result": "O",
      "moves": 62,
      "timestamp": "2026-03-23T22:39:59.312402"
    },
    {
      "game_num": 1,
      "s1": "random",
      "s2": "absolu",
      "winner": "absolu",
      "result": "O",
      "moves": 62,
      "timestamp": "2026-03-23T22:40:03.678592"
    },
    {
      "game_num": 2,
      "s1": "random",
      "s2": "absolu",
      "winner": "absolu",
      "result": "O",
      "moves": 62,
      "timestamp": "2026-03-23T22:40:05.676587"
    },
    {
      "game_num": 3,
      "s1": "random",
      "s2": "absolu",
      "winner": "absolu",
      "result": "O",
      "moves": 63,
      "timestamp": "2026-03-23T22:40:08.036556"
    },
    {
      "game_num": 4,
      "s1": "random",
      "s2": "absolu",
      "winner": "absolu",
      "result": "O",
      "moves": 63,
      "timestamp": "2026-03-23T22:40:10.837309"
    },
    {
      "game_num": 1,
      "s1": "poids",
      "s2": "montecarlo",
      "winner": "montecarlo",
      "result": "O",
      "moves": 66,
      "timestamp": "2026-03-23T22:40:15.216204"
    },
    {
      "game_num": 2,
      "s1": "poids",
      "s2": "montecarlo",
      "winner": "montecarlo",
      "result": "O",
      "moves": 68,
      "timestamp": "2026-03-23T22:40:18.971505"
    },
    {
      "game_num": 3,
      "s1": "poids",
      "s2": "montecarlo",
      "winner": "montecarlo",
      "result": "O",
      "moves": 63,
      "timestamp": "2026-03-23T22:40:24.568977"
    },
    {
      "game_num": 4,
      "s1": "poids",
      "s2": "montecarlo",
      "winner": "montecarlo",
      "result": "O",
      "moves": 64,
      "timestamp": "2026-03-23T22:40:28.722086"
    },
    {
      "game_num": 1,
      "s1": "poids",
      "s2": "random",
      "winner": "poids",
      "result": "X",
      "moves": 62,
      "timestamp": "2026-03-23T22:40:30.372196"
    },
    {
      "game_num": 2,
      "s1": "poids",
      "s2": "random",
      "winner": "random",
      "result": "O",
      "moves": 62,
      "timestamp": "2026-03-23T22:40:32.818981"
    },
    {
      "game_num": 3,
      "s1": "poids",
      "s2": "random",
      "winner": "random",
      "result": "O",
      "moves": 62,
      "timestamp": "2026-03-23T22:40:33.923011"
    },
    {
      "game_num": 4,
      "s1": "poids",
      "s2": "random",
      "winner": "poids",
      "result": "X",
      "moves": 62,
      "timestamp": "2026-03-23T22:40:34.830519"
    },
    {
      "game_num": 1,
      "s1": "poids",
      "s2": "mobilite",
      "winner": "poids",
      "result": "X",
      "moves": 62,
      "timestamp": "2026-03-23T22:40:37.893950"
    },
    {
      "game_num": 2,
      "s1": "poids",
      "s2": "mobilite",
      "winner": "poids",
      "result": "X",
      "moves": 62,
      "timestamp": "2026-03-23T22:40:40.981935"
    },
    {
      "game_num": 3,
      "s1": "poids",
      "s2": "mobilite",
      "winner": "poids",
      "result": "X",
      "moves": 62,
      "timestamp": "2026-03-23T22:40:44.053223"
    },
    {
      "game_num": 4,
      "s1": "poids",
      "s2": "mobilite",
      "winner": "poids",
      "result": "X",
      "moves": 62,
      "timestamp": "2026-03-23T22:40:47.243788"
    },
    {
      "game_num": 1,
      "s1": "poids",
      "s2": "mixte",
      "winner": "poids",
      "result": "X",
      "moves": 62,
      "timestamp": "2026-03-23T22:40:50.361394"
    },
    {
      "game_num": 2,
      "s1": "poids",
      "s2": "mixte",
      "winner": "poids",
      "result": "X",
      "moves": 62,
      "timestamp": "2026-03-23T22:40:53.472970"
    },
    {
      "game_num": 3,
      "s1": "poids",
      "s2": "mixte",
      "winner": "poids",
      "result": "X",
      "moves": 62,
      "timestamp": "2026-03-23T22:40:56.571778"
    },
    {
      "game_num": 4,
      "s1": "poids",
      "s2": "mixte",
      "winner": "poids",
      "result": "X",
      "moves": 62,
      "timestamp": "2026-03-23T22:40:59.681172"
    },
    {
      "game_num": 1,
      "s1": "poids",
      "s2": "absolu",
      "winner": "poids",
      "result": "X",
      "moves": 62,
      "timestamp": "2026-03-23T22:41:02.887061"
    },
    {
      "game_num": 2,
      "s1": "poids",
      "s2": "absolu",
      "winner": "poids",
      "result": "X",
      "moves": 62,
      "timestamp": "2026-03-23T22:41:05.969738"
    },
    {
      "game_num": 3,
      "s1": "poids",
      "s2": "absolu",
      "winner": "poids",
      "result": "X",
      "moves": 62,
      "timestamp": "2026-03-23T22:41:09.095382"
    },
    {
      "game_num": 4,
      "s1": "poids",
      "s2": "absolu",
      "winner": "poids",
      "result": "X",
      "moves": 62,
      "timestamp": "2026-03-23T22:41:12.155914"
    },
    {
      "game_num": 1,
      "s1": "mobilite",
      "s2": "montecarlo",
      "winner": "montecarlo",
      "result": "O",
      "moves": 62,
      "timestamp": "2026-03-23T22:41:17.575717"
    },
    {
      "game_num": 2,
      "s1": "mobilite",
      "s2": "montecarlo",
      "winner": "montecarlo",
      "result": "O",
      "moves": 63,
      "timestamp": "2026-03-23T22:41:22.536549"
    },
    {
      "game_num": 3,
      "s1": "mobilite",
      "s2": "montecarlo",
      "winner": "montecarlo",
      "result": "O",
      "moves": 62,
      "timestamp": "2026-03-23T22:41:28.851234"
    },
    {
      "game_num": 4,
      "s1": "mobilite",
      "s2": "montecarlo",
      "winner": "mobilite",
      "result": "X",
      "moves": 63,
      "timestamp": "2026-03-23T22:41:33.909865"
    },
    {
      "game_num": 1,
      "s1": "mobilite",
      "s2": "random",
      "winner": "mobilite",
      "result": "X",
      "moves": 63,
      "timestamp": "2026-03-23T22:41:37.747070"
    },
    {
      "game_num": 2,
      "s1": "mobilite",
      "s2": "random",
      "winner": "mobilite",
      "result": "X",
      "moves": 63,
      "timestamp": "2026-03-23T22:41:39.488878"
    },
    {
      "game_num": 3,
      "s1": "mobilite",
      "s2": "random",
      "winner": "mobilite",
      "result": "X",
      "moves": 62,
      "timestamp": "2026-03-23T22:41:43.591032"
    },
    {
      "game_num": 4,
      "s1": "mobilite",
      "s2": "random",
      "winner": "mobilite",
      "result": "X",
      "moves": 62,
      "timestamp": "2026-03-23T22:41:45.248133"
    },
    {
      "game_num": 1,
      "s1": "mobilite",
      "s2": "poids",
      "winner": "mobilite",
      "result": "X",
      "moves": 62,
      "timestamp": "2026-03-23T22:41:48.322651"
    },
    {
      "game_num": 2,
      "s1": "mobilite",
      "s2": "poids",
      "winner": "mobilite",
      "result": "X",
      "moves": 62,
      "timestamp": "2026-03-23T22:41:51.529249"
    },
    {
      "game_num": 3,
      "s1": "mobilite",
      "s2": "poids",
      "winner": "mobilite",
      "result": "X",
      "moves": 62,
      "timestamp": "2026-03-23T22:41:54.775060"
    },
    {
      "game_num": 4,
      "s1": "mobilite",
      "s2": "poids",
      "winner": "mobilite",
      "result": "X",
      "moves": 62,
      "timestamp": "2026-03-23T22:41:57.828520"
    },
    {
      "game_num": 1,
      "s1": "mobilite",
      "s2": "mixte",
      "winner": "mobilite",
      "result": "X",
      "moves": 62,
      "timestamp": "2026-03-23T22:42:01.007949"
    },
    {
      "game_num": 2,
      "s1": "mobilite",
      "s2": "mixte",
      "winner": "mobilite",
      "result": "X",
      "moves": 62,
      "timestamp": "2026-03-23T22:42:04.094822"
    },
    {
      "game_num": 3,
      "s1": "mobilite",
      "s2": "mixte",
      "winner": "mobilite",
      "result": "X",
      "moves": 62,
      "timestamp": "2026-03-23T22:42:07.137530"
    },
    {
      "game_num": 4,
      "s1": "mobilite",
      "s2": "mixte",
      "winner": "mobilite",
      "result": "X",
      "moves": 62,
      "timestamp": "2026-03-23T22:42:10.182600"
    },
    {
      "game_num": 1,
      "s1": "mobilite",
      "s2": "absolu",
      "winner": "mobilite",
      "result": "X",
      "moves": 62,
      "timestamp": "2026-03-23T22:42:13.238947"
    },
    {
      "game_num": 2,
      "s1": "mobilite",
      "s2": "absolu",
      "winner": "mobilite",
      "result": "X",
      "moves": 62,
      "timestamp": "2026-03-23T22:42:16.298827"
    },
    {
      "game_num": 3,
      "s1": "mobilite",
      "s2": "absolu",
      "winner": "mobilite",
      "result": "X",
      "moves": 62,
      "timestamp": "2026-03-23T22:42:19.347602"
    },
    {
      "game_num": 4,
      "s1": "mobilite",
      "s2": "absolu",
      "winner": "mobilite",
      "result": "X",
      "moves": 62,
      "timestamp": "2026-03-23T22:42:22.735400"
    },
    {
      "game_num": 1,
      "s1": "mixte",
      "s2": "montecarlo",
      "winner": "montecarlo",
      "result": "O",
      "moves": 65,
      "timestamp": "2026-03-23T22:42:27.543602"
    },
    {
      "game_num": 2,
      "s1": "mixte",
      "s2": "montecarlo",
      "winner": "montecarlo",
      "result": "O",
      "moves": 63,
      "timestamp": "2026-03-23T22:42:32.432737"
    },
    {
      "game_num": 3,
      "s1": "mixte",
      "s2": "montecarlo",
      "winner": "montecarlo",
      "result": "O",
      "moves": 62,
      "timestamp": "2026-03-23T22:42:37.924329"
    },
    {
      "game_num": 4,
      "s1": "mixte",
      "s2": "montecarlo",
      "winner": "montecarlo",
      "result": "O",
      "moves": 62,
      "timestamp": "2026-03-23T22:42:44.528259"
    },
    {
      "game_num": 1,
      "s1": "mixte",
      "s2": "random",
      "winner": "random",
      "result": "O",
      "moves": 64,
      "timestamp": "2026-03-23T22:42:46.048832"
    },
    {
      "game_num": 2,
      "s1": "mixte",
      "s2": "random",
      "winner": "random",
      "result": "O",
      "moves": 62,
      "timestamp": "2026-03-23T22:42:48.167565"
    },
    {
      "game_num": 3,
      "s1": "mixte",
      "s2": "random",
      "winner": "Égalité",
      "result": "Egalite",
      "moves": 62,
      "timestamp": "2026-03-23T22:42:49.623443"
    },
    {
      "game_num": 4,
      "s1": "mixte",
      "s2": "random",
      "winner": "mixte",
      "result": "X",
      "moves": 62,
      "timestamp": "2026-03-23T22:42:52.216771"
    },
    {
      "game_num": 1,
      "s1": "mixte",
      "s2": "poids",
      "winner": "mixte",
      "result": "X",
      "moves": 62,
      "timestamp": "2026-03-23T22:42:55.767470"
    },
    {
      "game_num": 2,
      "s1": "mixte",
      "s2": "poids",
      "winner": "mixte",
      "result": "X",
      "moves": 62,
      "timestamp": "2026-03-23T22:42:59.046892"
    },
    {
      "game_num": 3,
      "s1": "mixte",
      "s2": "poids",
      "winner": "mixte",
      "result": "X",
      "moves": 62,
      "timestamp": "2026-03-23T22:43:02.573148"
    },
    {
      "game_num": 4,
      "s1": "mixte",
      "s2": "poids",
      "winner": "mixte",
      "result": "X",
      "moves": 62,
      "timestamp": "2026-03-23T22:43:06.187206"
    },
    {
      "game_num": 1,
      "s1": "mixte",
      "s2": "mobilite",
      "winner": "mixte",
      "result": "X",
      "moves": 62,
      "timestamp": "2026-03-23T22:43:09.492398"
    },
    {
      "game_num": 2,
      "s1": "mixte",
      "s2": "mobilite",
      "winner": "mixte",
      "result": "X",
      "moves": 62,
      "timestamp": "2026-03-23T22:43:13.319342"
    },
    {
      "game_num": 3,
      "s1": "mixte",
      "s2": "mobilite",
      "winner": "mixte",
      "result": "X",
      "moves": 62,
      "timestamp": "2026-03-23T22:43:17.648630"
    },
    {
      "game_num": 4,
      "s1": "mixte",
      "s2": "mobilite",
      "winner": "mixte",
      "result": "X",
      "moves": 62,
      "timestamp": "2026-03-23T22:43:21.285774"
    },
    {
      "game_num": 1,
      "s1": "mixte",
      "s2": "absolu",
      "winner": "mixte",
      "result": "X",
      "moves": 62,
      "timestamp": "2026-03-23T22:43:25.024215"
    },
    {
      "game_num": 2,
      "s1": "mixte",
      "s2": "absolu",
      "winner": "mixte",
      "result": "X",
      "moves": 62,
      "timestamp": "2026-03-23T22:43:28.709204"
    },
    {
      "game_num": 3,
      "s1": "mixte",
      "s2": "absolu",
      "winner": "mixte",
      "result": "X",
      "moves": 62,
      "timestamp": "2026-03-23T22:43:32.095439"
    },
    {
      "game_num": 4,
      "s1": "mixte",
      "s2": "absolu",
      "winner": "mixte",
      "result": "X",
      "moves": 62,
      "timestamp": "2026-03-23T22:43:35.611577"
    },
    {
      "game_num": 1,
      "s1": "absolu",
      "s2": "montecarlo",
      "winner": "montecarlo",
      "result": "O",
      "moves": 62,
      "timestamp": "2026-03-23T22:43:40.839255"
    },
    {
      "game_num": 2,
      "s1": "absolu",
      "s2": "montecarlo",
      "winner": "montecarlo",
      "result": "O",
      "moves": 63,
      "timestamp": "2026-03-23T22:43:48.093553"
    },
    {
      "game_num": 3,
      "s1": "absolu",
      "s2": "montecarlo",
      "winner": "montecarlo",
      "result": "O",
      "moves": 64,
      "timestamp": "2026-03-23T22:43:53.188891"
    },
    {
      "game_num": 4,
      "s1": "absolu",
      "s2": "montecarlo",
      "winner": "absolu",
      "result": "X",
      "moves": 63,
      "timestamp": "2026-03-23T22:43:59.216474"
    },
    {
      "game_num": 1,
      "s1": "absolu",
      "s2": "random",
      "winner": "random",
      "result": "O",
      "moves": 62,
      "timestamp": "2026-03-23T22:44:00.453019"
    },
    {
      "game_num": 2,
      "s1": "absolu",
      "s2": "random",
      "winner": "random",
      "result": "O",
      "moves": 66,
      "timestamp": "2026-03-23T22:44:02.960254"
    },
    {
      "game_num": 3,
      "s1": "absolu",
      "s2": "random",
      "winner": "absolu",
      "result": "X",
      "moves": 63,
      "timestamp": "2026-03-23T22:44:06.127240"
    },
    {
      "game_num": 4,
      "s1": "absolu",
      "s2": "random",
      "winner": "random",
      "result": "O",
      "moves": 64,
      "timestamp": "2026-03-23T22:44:08.770309"
    },
    {
      "game_num": 1,
      "s1": "absolu",
      "s2": "poids",
      "winner": "absolu",
      "result": "X",
      "moves": 62,
      "timestamp": "2026-03-23T22:44:12.224037"
    },
    {
      "game_num": 2,
      "s1": "absolu",
      "s2": "poids",
      "winner": "absolu",
      "result": "X",
      "moves": 62,
      "timestamp": "2026-03-23T22:44:15.592660"
    },
    {
      "game_num": 3,
      "s1": "absolu",
      "s2": "poids",
      "winner": "absolu",
      "result": "X",
      "moves": 62,
      "timestamp": "2026-03-23T22:44:19.167760"
    },
    {
      "game_num": 4,
      "s1": "absolu",
      "s2": "poids",
      "winner": "absolu",
      "result": "X",
      "moves": 62,
      "timestamp": "2026-03-23T22:44:22.702131"
    },
    {
      "game_num": 1,
      "s1": "absolu",
      "s2": "mobilite",
      "winner": "absolu",
      "result": "X",
      "moves": 62,
      "timestamp": "2026-03-23T22:44:26.291242"
    },
    {
      "game_num": 2,
      "s1": "absolu",
      "s2": "mobilite",
      "winner": "absolu",
      "result": "X",
      "moves": 62,
      "timestamp": "2026-03-23T22:44:29.864532"
    },
    {
      "game_num": 3,
      "s1": "absolu",
      "s2": "mobilite",
      "winner": "absolu",
      "result": "X",
      "moves": 62,
      "timestamp": "2026-03-23T22:44:33.452830"
    },
    {
      "game_num": 4,
      "s1": "absolu",
      "s2": "mobilite",
      "winner": "absolu",
      "result": "X",
      "moves": 62,
      "timestamp": "2026-03-23T22:44:37.032967"
    },
    {
      "game_num": 1,
      "s1": "absolu",
      "s2": "mixte",
      "winner": "absolu",
      "result": "X",
      "moves": 62,
      "timestamp": "2026-03-23T22:44:40.562133"
    },
    {
      "game_num": 2,
      "s1": "absolu",
      "s2": "mixte",
      "winner": "absolu",
      "result": "X",
      "moves": 62,
      "timestamp": "2026-03-23T22:44:44.248482"
    },
    {
      "game_num": 3,
      "s1": "absolu",
      "s2": "mixte",
      "winner": "absolu",
      "result": "X",
      "moves": 62,
      "timestamp": "2026-03-23T22:44:47.721037"
    },
    {
      "game_num": 4,
      "s1": "absolu",
      "s2": "mixte",
      "winner": "absolu",
      "result": "X",
      "moves": 62,
      "timestamp": "2026-03-23T22:44:51.256702"
    }
  ]
}